ranky/__init__.py
ranky/duel.py
ranky/generator.py
ranky/metric.py
ranky/pairwise.py
ranky/ranking.py
ranky/utilities.py
ranky/visualization.py
ranky-0.3.7.dist-info/LICENSE
ranky-0.3.7.dist-info/METADATA
ranky-0.3.7.dist-info/WHEEL
ranky-0.3.7.dist-info/top_level.txt
ranky-0.3.7.dist-info/RECORD
