Metadata-Version: 2.1
Name: ranky
Version: 0.3.7
Summary: Compute rankings in Python.
Home-page: https://github.com/didayolo/ranky
Author: Adrien Pavao
Author-email: adrien.pavao@gmail.com
Project-URL: Bug Tracker, https://github.com/didayolo/ranky/issues
Project-URL: Documentation, https://didayolo.github.io/ranky/
Project-URL: Source Code, https://github.com/didayolo/ranky
Classifier: Programming Language :: Python :: 3
Classifier: Operating System :: Unix
License-File: LICENSE
Requires-Dist: pandas
Requires-Dist: numpy
Requires-Dist: matplotlib
Requires-Dist: scikit-learn >=1.0
Requires-Dist: scipy >=1.7.0
Requires-Dist: seaborn
Requires-Dist: networkx
Requires-Dist: python-Levenshtein
Requires-Dist: tqdm
Requires-Dist: baycomp
